<mvc:View controllerName="logo.controller.logo"
    xmlns:mvc="sap.ui.core.mvc" displayBlock="true"
    xmlns="sap.m">
    <Page id="page" title="{i18n>title}">
        <content>
     <HBox id="_IDGenHBox1" >
        
        
          <GenericTile id="_IDGenGenericTile2" class="sapUiTinyMarginBegin sapUiTinyMarginTop tileLayout" header="Country-Specific Profit Margin"  press="_pagesalesdocument3"
		frameType="OneByHalf" subheader="Subtitle">
		<TileContent id="_IDGenTileContent2">
			<ImageContent id="_IDGenImageContent2" src="test-resources/sap/m/demokit/sample/GenericTileAsLaunchTile/images/SAPLogoLargeTile_28px_height.png" />
		</TileContent>
	</GenericTile>

    <GenericTile id="_IDGenGenericTile3" class="sapUiTinyMarginBegin sapUiTinyMarginTop tileLayout" header="Sales Fulfillment Application Title"
		subheader="Subtitle" press="_pagesalesdocument2">
		<TileContent id="_IDGenTileContent3" unit="EUR" footer="Current Quarter">
			<ImageContent id="_IDGenImageContent3" src="sap-icon://home-share" />
		</TileContent>
	</GenericTile>

    <GenericTile id="_IDGenGenericTile4"
	    class="sapUiTinyMarginBegin sapUiTinyMarginTop tileLayout" 
	    header="SALES"
		subheader="sales document" 
		press="_pagesalesdocument1" url="https://www.sap.com/">
		<TileContent id="_IDGenTileContent4">
			<ImageContent id="_IDGenImageContent4" src="sap-icon://sales-order-item" />
		</TileContent>
	</GenericTile>

        </HBox>
        
        </content>
    </Page>
</mvc:View>
